cyborgdb/.gitignore
cyborgdb/__init__.py
cyborgdb/openapi_client_README.md
cyborgdb/client/__init__.py
cyborgdb/client/client.py
cyborgdb/client/encrypted_index.py
cyborgdb/integrations/__init__.py
cyborgdb/integrations/langchain.py
cyborgdb/openapi_client/__init__.py
cyborgdb/openapi_client/api_client.py
cyborgdb/openapi_client/api_response.py
cyborgdb/openapi_client/configuration.py
cyborgdb/openapi_client/exceptions.py
cyborgdb/openapi_client/py.typed
cyborgdb/openapi_client/rest.py
cyborgdb/openapi_client/api/__init__.py
cyborgdb/openapi_client/api/default_api.py
cyborgdb/openapi_client/models/__init__.py
cyborgdb/openapi_client/models/batch_query_request.py
cyborgdb/openapi_client/models/contents.py
cyborgdb/openapi_client/models/create_index_request.py
cyborgdb/openapi_client/models/cyborgdb_service_api_schemas_index_success_response_model.py
cyborgdb/openapi_client/models/cyborgdb_service_api_schemas_vectors_success_response_model.py
cyborgdb/openapi_client/models/delete_request.py
cyborgdb/openapi_client/models/error_response_model.py
cyborgdb/openapi_client/models/get_request.py
cyborgdb/openapi_client/models/get_response_model.py
cyborgdb/openapi_client/models/get_result_item_model.py
cyborgdb/openapi_client/models/http_validation_error.py
cyborgdb/openapi_client/models/index_config.py
cyborgdb/openapi_client/models/index_info_response_model.py
cyborgdb/openapi_client/models/index_ivf_flat_model.py
cyborgdb/openapi_client/models/index_ivf_model.py
cyborgdb/openapi_client/models/index_ivfpq_model.py
cyborgdb/openapi_client/models/index_list_response_model.py
cyborgdb/openapi_client/models/index_operation_request.py
cyborgdb/openapi_client/models/index_training_status_response_model.py
cyborgdb/openapi_client/models/list_ids_request.py
cyborgdb/openapi_client/models/list_ids_response.py
cyborgdb/openapi_client/models/query_request.py
cyborgdb/openapi_client/models/query_response.py
cyborgdb/openapi_client/models/query_result_item.py
cyborgdb-0.12.0.dist-info/licenses/LICENSE
cyborgdb-0.12.0.dist-info/METADATA
cyborgdb-0.12.0.dist-info/WHEEL
cyborgdb-0.12.0.dist-info/top_level.txt
cyborgdb-0.12.0.dist-info/RECORD
