Metadata-Version: 2.4
Name: cyborgdb
Version: 0.12.0
Summary: Python Client SDK for CyborgDB: The Confidential Vector Database
Author: Cyborg Inc.
License: MIT
Project-URL: Homepage, https://www.cyborg.co
Project-URL: Documentation, https://docs.cyborg.co
Project-URL: Repository, https://github.com/cyborginc/cyborgdb-py
Keywords: OpenAPI,OpenAPI-Generator,CyborgDB Service
Classifier: Intended Audience :: Developers
Classifier: Intended Audience :: Information Technology
Classifier: Operating System :: OS Independent
Classifier: Programming Language :: Python :: 3
Classifier: Programming Language :: Python :: 3.8
Classifier: Programming Language :: Python :: 3.9
Classifier: Programming Language :: Python :: 3.10
Classifier: Programming Language :: Python :: 3.11
Classifier: Programming Language :: Python :: 3.12
Classifier: Programming Language :: Python :: 3.13
Classifier: Programming Language :: C++
Classifier: Topic :: Database
Classifier: Topic :: Database :: Database Engines/Servers
Classifier: Topic :: Security :: Cryptography
Classifier: Topic :: Software Development :: Libraries
Requires-Python: >=3.8
License-File: LICENSE
Requires-Dist: urllib3<3.0.0,>=1.25.3
Requires-Dist: python-dateutil>=2.8.2
Requires-Dist: pydantic>=2
Requires-Dist: typing-extensions>=4.7.1
Requires-Dist: python-dotenv>=0.19.0
Provides-Extra: langchain
Requires-Dist: langchain-core>=0.1.0; extra == "langchain"
Requires-Dist: sentence-transformers>=2.2.0; extra == "langchain"
Requires-Dist: numpy>=1.21.0; extra == "langchain"
Dynamic: license-file
